LICENSE
MANIFEST.in
README.md
setup.cfg
setup.py
tilejet_stats.egg-info/PKG-INFO
tilejet_stats.egg-info/SOURCES.txt
tilejet_stats.egg-info/dependency_links.txt
tilejet_stats.egg-info/top_level.txt
tilejetstats/__init__.py
tilejetstats/base.py
tilejetstats/mongodb.py
tilejetstats/tilestats.py