Metadata-Version: 1.1
Name: tilejet-stats
Version: 0.0.2
Summary: A python utility library containing functions for generating statistics on tile service usage.
Home-page: https://github.com/tilejet/tilejet-stats/
Author: TileJet Developers
Author-email: tilejet.dev@gmail.com
License: MIT License
Download-URL: https://github.com/tilejet/tilejet-stats/zipball/master
Keywords: python gis tilejet
Platform: UNKNOWN
Classifier: Development Status :: 4 - Beta
Classifier: Intended Audience :: Developers
Classifier: License :: OSI Approved :: MIT License
Classifier: Topic :: Software Development :: Libraries :: Python Modules
